README.rst
setup.cfg
setup.py
vkhealth/__init__.py
vkhealth.egg-info/PKG-INFO
vkhealth.egg-info/SOURCES.txt
vkhealth.egg-info/dependency_links.txt
vkhealth.egg-info/top_level.txt