Metadata-Version: 1.1
Name: vkhealth
Version: 0.6
Summary: Module that shows the current health of the VKontakte platform
Home-page: https://github.com/DaniilChizhevskii/vkhealth
Author: Daniil Chizhevskij
Author-email: daniilchizhevskij@gmail.com
License: UNKNOWN
Platform: UNKNOWN
Classifier: Programming Language :: Python :: 3
Classifier: License :: OSI Approved :: GNU General Public License v3 (GPLv3)
Classifier: Operating System :: OS Independent
